PygameTool/Canvas.py
PygameTool/Radio.py
PygameTool/Scrollbar.py
PygameTool/__init__.py
PygameTool/button.py
PygameTool/circle.py
PygameTool/dropDown.py
PygameTool/functool.py
PygameTool/inputBox.py
PygameTool/line.py
PygameTool/music.py
PygameTool/rectangle.py
PygameTool/seekBar.py
PygameTool/setup.py
PygameTool/sprite.py
PygameTool/starfield.py
PygameTool/text.py
PygameTool/tk_messageBox.py
pygametool_rui-0.1.1.dist-info/METADATA
pygametool_rui-0.1.1.dist-info/WHEEL
pygametool_rui-0.1.1.dist-info/top_level.txt
pygametool_rui-0.1.1.dist-info/RECORD
